{
    "三水": [
        "三水南"
    ],
    "三穗": [
        "三穗"
    ],
    "三门": [
        "三门县"
    ],
    "三门峡": [
        "三门峡南"
    ],
    "上海": [
        "上海虹桥",
        "上海",
        "上海西"
    ],
    "上虞": [
        "上虞北"
    ],
    "上饶": [
        "上饶"
    ],
    "东安": [
        "东安东"
    ],
    "丰都": [
        "丰都"
    ],
    "临汾": [
        "临汾西"
    ],
    "临海": [
        "临海"
    ],
    "丹东": [
        "丹东"
    ],
    "丹徒": [
        "丹徒"
    ],
    "丹阳": [
        "丹阳北",
        "丹阳"
    ],
    "丽水": [
        "丽水"
    ],
    "义乌": [
        "义乌"
    ],
    "乐清": [
        "乐清"
    ],
    "云浮": [
        "云浮东"
    ],
    "五府": [
        "五府山"
    ],
    "五龙背": [
        "五龙背东"
    ],
    "介休": [
        "介休东"
    ],
    "仙林": [
        "仙林"
    ],
    "仙桃": [
        "仙桃西"
    ],
    "仙游": [
        "仙游"
    ],
    "余姚": [
        "余姚北"
    ],
    "余杭": [
        "余杭"
    ],
    "侯马": [
        "侯马西"
    ],
    "保定": [
        "保定东"
    ],
    "信阳": [
        "信阳东"
    ],
    "光明": [
        "光明城"
    ],
    "全州": [
        "全州南"
    ],
    "全椒": [
        "全椒"
    ],
    "公主岭": [
        "公主岭南"
    ],
    "六安": [
        "六安"
    ],
    "兴安": [
        "兴安北"
    ],
    "内江": [
        "内江北"
    ],
    "军粮城": [
        "军粮城北"
    ],
    "凤城": [
        "凤城东"
    ],
    "凯里": [
        "凯里南"
    ],
    "利川": [
        "利川"
    ],
    "北京": [
        "北京南",
        "北京西"
    ],
    "北戴": [
        "北戴河"
    ],
    "北海": [
        "北海"
    ],
    "华山": [
        "华山北"
    ],
    "南京": [
        "南京南",
        "南京"
    ],
    "南宁": [
        "南宁东",
        "南宁"
    ],
    "南平": [
        "南平北"
    ],
    "南昌": [
        "南昌西"
    ],
    "南江": [
        "南江口"
    ],
    "南翔": [
        "南翔北"
    ],
    "南陵": [
        "南陵"
    ],
    "即墨": [
        "即墨北"
    ],
    "厦门": [
        "厦门北",
        "厦门"
    ],
    "双城": [
        "双城北"
    ],
    "双峰": [
        "双峰北"
    ],
    "古田": [
        "古田北"
    ],
    "句容": [
        "句容西"
    ],
    "台安": [
        "台安"
    ],
    "台州": [
        "台州"
    ],
    "合川": [
        "合川"
    ],
    "合肥": [
        "合肥南",
        "合肥",
        "合肥北城"
    ],
    "吉林": [
        "吉林"
    ],
    "咸宁": [
        "咸宁北"
    ],
    "咸阳": [
        "咸阳秦都"
    ],
    "哈尔滨": [
        "哈尔滨西"
    ],
    "唐山": [
        "唐山"
    ],
    "嘉兴": [
        "嘉兴南"
    ],
    "嘉善": [
        "嘉善南"
    ],
    "四平": [
        "四平东"
    ],
    "图们": [
        "图们北"
    ],
    "大英": [
        "大英东"
    ],
    "大足": [
        "大足南"
    ],
    "大连": [
        "大连北",
        "大连"
    ],
    "天津": [
        "天津南",
        "天津西",
        "天津"
    ],
    "天门": [
        "天门南"
    ],
    "太原": [
        "太原南"
    ],
    "太谷": [
        "太谷西"
    ],
    "奉化": [
        "奉化"
    ],
    "威海": [
        "威海"
    ],
    "娄底": [
        "娄底南"
    ],
    "婺源": [
        "婺源"
    ],
    "孝感": [
        "孝感北"
    ],
    "宁德": [
        "宁德"
    ],
    "宁波": [
        "宁波"
    ],
    "宁海": [
        "宁海"
    ],
    "安亭": [
        "安亭北"
    ],
    "安图": [
        "安图西"
    ],
    "安庆": [
        "安庆"
    ],
    "安阳": [
        "安阳东"
    ],
    "定州": [
        "定州东"
    ],
    "定远": [
        "定远"
    ],
    "宜兴": [
        "宜兴"
    ],
    "宜昌": [
        "宜昌东"
    ],
    "宜春": [
        "宜春"
    ],
    "宝华": [
        "宝华山"
    ],
    "宝鸡": [
        "宝鸡南"
    ],
    "宾阳": [
        "宾阳"
    ],
    "宿州": [
        "宿州东"
    ],
    "山海": [
        "山海关"
    ],
    "岐山": [
        "岐山"
    ],
    "岳阳": [
        "岳阳东"
    ],
    "巢湖": [
        "巢湖东"
    ],
    "巩义": [
        "巩义南"
    ],
    "常州": [
        "常州北",
        "常州"
    ],
    "平南": [
        "平南南"
    ],
    "平遥": [
        "平遥古城"
    ],
    "广宁": [
        "广宁"
    ],
    "广州": [
        "广州南",
        "广州北"
    ],
    "庄桥": [
        "庄桥"
    ],
    "庆盛": [
        "庆盛"
    ],
    "廊坊": [
        "廊坊"
    ],
    "延吉": [
        "延吉西"
    ],
    "建始": [
        "建始"
    ],
    "建瓯": [
        "建瓯西"
    ],
    "开原": [
        "开原西"
    ],
    "弋江": [
        "弋江"
    ],
    "弋阳": [
        "弋阳"
    ],
    "当涂": [
        "当涂东"
    ],
    "徐州": [
        "徐州东"
    ],
    "德兴": [
        "德兴"
    ],
    "德州": [
        "德州东"
    ],
    "德惠": [
        "德惠西"
    ],
    "德清": [
        "德清"
    ],
    "怀化": [
        "怀化南"
    ],
    "怀集": [
        "怀集"
    ],
    "恩施": [
        "恩施"
    ],
    "恭城": [
        "恭城"
    ],
    "惠东": [
        "惠东"
    ],
    "惠安": [
        "惠安"
    ],
    "惠山": [
        "惠山"
    ],
    "惠州": [
        "惠州南"
    ],
    "成都": [
        "成都东"
    ],
    "戚墅": [
        "戚墅堰"
    ],
    "扶余": [
        "扶余北"
    ],
    "抚州": [
        "抚州东"
    ],
    "敦化": [
        "敦化"
    ],
    "文登": [
        "文登东"
    ],
    "新乡": [
        "新乡东"
    ],
    "新余": [
        "新余北"
    ],
    "新化": [
        "新化南"
    ],
    "新晃": [
        "新晃西"
    ],
    "旌德": [
        "旌德"
    ],
    "无为": [
        "无为"
    ],
    "无锡": [
        "无锡东",
        "无锡",
        "无锡新区"
    ],
    "昆山": [
        "昆山南"
    ],
    "昌乐": [
        "昌乐"
    ],
    "昌图": [
        "昌图西"
    ],
    "明港": [
        "明港东"
    ],
    "晋中": [
        "晋中"
    ],
    "晋江": [
        "晋江"
    ],
    "普宁": [
        "普宁"
    ],
    "普湾": [
        "普湾"
    ],
    "曲阜": [
        "曲阜东"
    ],
    "本溪": [
        "本溪",
        "本溪新城"
    ],
    "来宾": [
        "来宾北"
    ],
    "杨陵": [
        "杨陵南"
    ],
    "杭州": [
        "杭州东",
        "杭州"
    ],
    "松江": [
        "松江南"
    ],
    "枝江": [
        "枝江北"
    ],
    "枣庄": [
        "枣庄"
    ],
    "柳州": [
        "柳州"
    ],
    "株洲": [
        "株洲西"
    ],
    "桂平": [
        "桂平"
    ],
    "桂林": [
        "桂林",
        "桂林北"
    ],
    "桃村": [
        "桃村北"
    ],
    "桐乡": [
        "桐乡"
    ],
    "梧州": [
        "梧州南"
    ],
    "歙县": [
        "歙县北"
    ],
    "正定": [
        "正定机场"
    ],
    "武义": [
        "武义北"
    ],
    "武夷山": [
        "武夷山东",
        "武夷山北"
    ],
    "武汉": [
        "武汉"
    ],
    "水家湖": [
        "水家湖"
    ],
    "永嘉": [
        "永嘉"
    ],
    "永川": [
        "永川东"
    ],
    "永州": [
        "永州"
    ],
    "永康": [
        "永康南"
    ],
    "永济": [
        "永济北"
    ],
    "永福": [
        "永福南"
    ],
    "汉口": [
        "汉口"
    ],
    "汉川": [
        "汉川"
    ],
    "汕尾": [
        "汕尾"
    ],
    "江宁": [
        "江宁",
        "江宁西"
    ],
    "江山": [
        "江山"
    ],
    "池州": [
        "池州"
    ],
    "汨罗": [
        "汨罗东"
    ],
    "沈阳": [
        "沈阳北",
        "沈阳",
        "沈阳南"
    ],
    "沧州": [
        "沧州西"
    ],
    "泉州": [
        "泉州"
    ],
    "泰安": [
        "泰安"
    ],
    "泾县": [
        "泾县"
    ],
    "洛阳": [
        "洛阳龙门"
    ],
    "洪洞": [
        "洪洞西"
    ],
    "济南": [
        "济南西",
        "济南"
    ],
    "海城": [
        "海城西"
    ],
    "海宁": [
        "海宁西"
    ],
    "海阳": [
        "海阳北"
    ],
    "涪陵": [
        "涪陵北"
    ],
    "涵江": [
        "涵江"
    ],
    "涿州": [
        "涿州东"
    ],
    "淄博": [
        "淄博"
    ],
    "淮南": [
        "淮南东"
    ],
    "深圳": [
        "深圳北",
        "深圳坪山"
    ],
    "清远": [
        "清远"
    ],
    "渑池": [
        "渑池南"
    ],
    "温岭": [
        "温岭"
    ],
    "温州": [
        "温州南"
    ],
    "渭南": [
        "渭南北"
    ],
    "湖州": [
        "湖州"
    ],
    "湘潭": [
        "湘潭北"
    ],
    "溆浦": [
        "溆浦南"
    ],
    "溧水": [
        "溧水"
    ],
    "溧阳": [
        "溧阳"
    ],
    "滁州": [
        "滁州"
    ],
    "滕州": [
        "滕州东"
    ],
    "滦河": [
        "滦河"
    ],
    "滨海": [
        "滨海北",
        "滨海"
    ],
    "漯河": [
        "漯河西"
    ],
    "漳州": [
        "漳州"
    ],
    "潍坊": [
        "潍坊"
    ],
    "潜江": [
        "潜江"
    ],
    "潮汕": [
        "潮汕"
    ],
    "潮阳": [
        "潮阳"
    ],
    "潼南": [
        "潼南"
    ],
    "灵宝": [
        "灵宝西"
    ],
    "烟台": [
        "烟台",
        "烟台南"
    ],
    "牟平": [
        "牟平"
    ],
    "玉山": [
        "玉山南"
    ],
    "珲春": [
        "珲春"
    ],
    "瑞安": [
        "瑞安"
    ],
    "璧山": [
        "璧山"
    ],
    "瓦屋": [
        "瓦屋山"
    ],
    "瓦房店": [
        "瓦房店西"
    ],
    "白沟": [
        "白沟"
    ],
    "白洋": [
        "白洋淀"
    ],
    "盖州": [
        "盖州西"
    ],
    "盘锦": [
        "盘锦",
        "盘锦北"
    ],
    "石家": [
        "石家庄"
    ],
    "石柱": [
        "石柱县"
    ],
    "祁东": [
        "祁东"
    ],
    "祁阳": [
        "祁阳"
    ],
    "福州": [
        "福州",
        "福州南"
    ],
    "福清": [
        "福清"
    ],
    "福田": [
        "福田"
    ],
    "福鼎": [
        "福鼎"
    ],
    "秦皇": [
        "秦皇岛"
    ],
    "章丘": [
        "章丘"
    ],
    "简阳": [
        "简阳南"
    ],
    "繁昌": [
        "繁昌西"
    ],
    "红安": [
        "红安西"
    ],
    "绅坊": [
        "绅坊"
    ],
    "绍兴": [
        "绍兴北"
    ],
    "绥中": [
        "绥中北"
    ],
    "绩溪": [
        "绩溪北"
    ],
    "缙云": [
        "缙云西"
    ],
    "耒阳": [
        "耒阳西"
    ],
    "肇庆": [
        "肇庆东"
    ],
    "肥东": [
        "肥东"
    ],
    "胜芳": [
        "胜芳"
    ],
    "胶州": [
        "胶州北"
    ],
    "芜湖": [
        "芜湖"
    ],
    "花桥": [
        "花桥"
    ],
    "芷江": [
        "芷江"
    ],
    "苍南": [
        "苍南"
    ],
    "苏州": [
        "苏州北",
        "苏州",
        "苏州园区",
        "苏州新区"
    ],
    "英德": [
        "英德西"
    ],
    "荆州": [
        "荆州"
    ],
    "荣成": [
        "荣成"
    ],
    "荣昌": [
        "荣昌北"
    ],
    "莆田": [
        "莆田"
    ],
    "莱西": [
        "莱西北"
    ],
    "莱阳": [
        "莱阳"
    ],
    "萍乡": [
        "萍乡北"
    ],
    "营口": [
        "营口东"
    ],
    "葫芦岛": [
        "葫芦岛北"
    ],
    "葵潭": [
        "葵潭"
    ],
    "虎门": [
        "虎门"
    ],
    "蚌埠": [
        "蚌埠南"
    ],
    "蛟河": [
        "蛟河西"
    ],
    "衡山": [
        "衡山西"
    ],
    "衡阳": [
        "衡阳东"
    ],
    "衢州": [
        "衢州"
    ],
    "西安": [
        "西安北"
    ],
    "许昌": [
        "许昌东"
    ],
    "诏安": [
        "诏安"
    ],
    "诸暨": [
        "诸暨"
    ],
    "贵定": [
        "贵定北"
    ],
    "贵港": [
        "贵港"
    ],
    "贵阳": [
        "贵阳北"
    ],
    "贺州": [
        "贺州"
    ],
    "资中": [
        "资中北"
    ],
    "资阳": [
        "资阳北"
    ],
    "赤壁": [
        "赤壁北"
    ],
    "辽中": [
        "辽中"
    ],
    "辽阳": [
        "辽阳"
    ],
    "运城": [
        "运城北"
    ],
    "进贤": [
        "进贤南"
    ],
    "通远堡": [
        "通远堡西"
    ],
    "邢台": [
        "邢台东"
    ],
    "邯郸": [
        "邯郸东"
    ],
    "邵东": [
        "邵东"
    ],
    "邵阳": [
        "邵阳北",
        "邵阳"
    ],
    "郁南": [
        "郁南"
    ],
    "郑州": [
        "郑州东",
        "郑州",
        "郑州西"
    ],
    "郴州": [
        "郴州西"
    ],
    "醴陵": [
        "醴陵东"
    ],
    "重庆": [
        "重庆北"
    ],
    "金华": [
        "金华",
        "金华南"
    ],
    "金寨": [
        "金寨"
    ],
    "金山": [
        "金山北"
    ],
    "钦州": [
        "钦州东"
    ],
    "铁岭": [
        "铁岭西"
    ],
    "铜仁": [
        "铜仁南"
    ],
    "铜陵": [
        "铜陵北",
        "铜陵"
    ],
    "锦州": [
        "锦州南"
    ],
    "镇江": [
        "镇江南",
        "镇江"
    ],
    "长临": [
        "长临河"
    ],
    "长兴": [
        "长兴"
    ],
    "长寿": [
        "长寿北"
    ],
    "长春": [
        "长春西",
        "长春"
    ],
    "长沙": [
        "长沙南"
    ],
    "闽清": [
        "闽清北"
    ],
    "阳泉": [
        "阳泉北"
    ],
    "阳澄": [
        "阳澄湖"
    ],
    "陆丰": [
        "陆丰"
    ],
    "隆昌": [
        "隆昌北"
    ],
    "雁荡山": [
        "雁荡山"
    ],
    "霍州": [
        "霍州东"
    ],
    "霞浦": [
        "霞浦"
    ],
    "霸州": [
        "霸州西"
    ],
    "青岛": [
        "青岛",
        "青岛北"
    ],
    "青州": [
        "青州市"
    ],
    "青田": [
        "青田"
    ],
    "鞍山": [
        "鞍山西"
    ],
    "韶关": [
        "韶关"
    ],
    "韶山": [
        "韶山南"
    ],
    "饶平": [
        "饶平"
    ],
    "马鞍山": [
        "马鞍山东"
    ],
    "驻马店": [
        "驻马店西"
    ],
    "高安": [
        "高安"
    ],
    "高密": [
        "高密"
    ],
    "高碑店": [
        "高碑店东"
    ],
    "高邑": [
        "高邑西"
    ],
    "鲅鱼": [
        "鲅鱼圈"
    ],
    "鲘门": [
        "鲘门"
    ],
    "鳌江": [
        "鳌江"
    ],
    "鹤壁": [
        "鹤壁东"
    ],
    "鹰潭": [
        "鹰潭北"
    ],
    "鹿寨": [
        "鹿寨北"
    ],
    "麻城": [
        "麻城北"
    ],
    "黄山": [
        "黄山北"
    ],
    "龙游": [
        "龙游"
    ]
}